lambda_packer/__init__.py
lambda_packer/cli.py
lambda_packer/config.py
lambda_packer/docker_utils.py
lambda_packer/file_utils.py
lambda_packer/package_utils.py
lambda_packer/template_utils.py
lambda_packer-0.1.51.dist-info/LICENSE
lambda_packer-0.1.51.dist-info/METADATA
lambda_packer-0.1.51.dist-info/WHEEL
lambda_packer-0.1.51.dist-info/entry_points.txt
lambda_packer-0.1.51.dist-info/top_level.txt
lambda_packer-0.1.51.dist-info/RECORD
