Metadata-Version: 2.1
Name: lambda_packer
Version: 0.1.51
Summary: A tool to package Python AWS Lambda functions with zips, Docker containers, and layers.
License: MIT
Classifier: Programming Language :: Python :: 3
Classifier: License :: OSI Approved :: MIT License
Classifier: Operating System :: OS Independent
Requires-Python: >=3.8
License-File: LICENSE
Requires-Dist: Click
Requires-Dist: PyYAML
Requires-Dist: docker
Provides-Extra: dev
Requires-Dist: pytest; extra == "dev"
Requires-Dist: pytest-mock; extra == "dev"
Requires-Dist: black; extra == "dev"
Requires-Dist: twine; extra == "dev"
Requires-Dist: bump2version; extra == "dev"
